mathics_scanner/__init__.py
mathics_scanner/characters.py
mathics_scanner/errors.py
mathics_scanner/escape_sequences.py
mathics_scanner/feed.py
mathics_scanner/load.py
mathics_scanner/location.py
mathics_scanner/mathics3_tokens.py
mathics_scanner/tokeniser-too-much.py
mathics_scanner/tokeniser.py
mathics_scanner/version.py
mathics_scanner/data/character-tables.json
mathics_scanner/data/element.csv
mathics_scanner/data/named-characters.yml
mathics_scanner/data/operators.json
mathics_scanner/data/operators.yml
mathics_scanner/generate/build_operator_tables.py
mathics_scanner/generate/build_tables.py
mathics_scanner/generate/rl_inputrc.py
mathics_scanner-2.0.0.dist-info/licenses/AUTHORS.txt
mathics_scanner-2.0.0.dist-info/licenses/COPYING.txt
mathics_scanner-2.0.0.dist-info/METADATA
mathics_scanner-2.0.0.dist-info/WHEEL
mathics_scanner-2.0.0.dist-info/entry_points.txt
mathics_scanner-2.0.0.dist-info/top_level.txt
mathics_scanner-2.0.0.dist-info/RECORD
