Metadata-Version: 2.4
Name: Mathics_Scanner
Version: 2.0.0
Summary: Character Tables and Tokenizer for Mathics and the Wolfram Language.
Maintainer: Mathics3 Group
License-Expression: GPL-3.0-or-later
Project-URL: Homepage, https://mathics.org/
Keywords: Mathematica,Wolfram,Interpreter,Shell,Math,CAS
Classifier: Intended Audience :: Developers
Classifier: Intended Audience :: Science/Research
Classifier: Programming Language :: Python
Classifier: Programming Language :: Python :: 3.10
Classifier: Programming Language :: Python :: 3.11
Classifier: Programming Language :: Python :: 3.12
Classifier: Programming Language :: Python :: 3.13
Classifier: Programming Language :: Python :: Implementation :: CPython
Classifier: Programming Language :: Python :: Implementation :: PyPy
Classifier: Topic :: Scientific/Engineering
Classifier: Topic :: Scientific/Engineering :: Mathematics
Classifier: Topic :: Scientific/Engineering :: Physics
Classifier: Topic :: Software Development :: Interpreters
Requires-Python: >=3.10
License-File: COPYING.txt
License-File: AUTHORS.txt
Requires-Dist: PyYAML
Requires-Dist: chardet
Requires-Dist: click
Provides-Extra: dev
Requires-Dist: pytest; extra == "dev"
Provides-Extra: full
Requires-Dist: ujson; extra == "full"
Dynamic: license-file
